README.md
setup.py
endandicrypto/__init__.py
endandicrypto/exception.py
endandicrypto/import_all.py
endandicrypto.egg-info/PKG-INFO
endandicrypto.egg-info/SOURCES.txt
endandicrypto.egg-info/dependency_links.txt
endandicrypto.egg-info/top_level.txt