Metadata-Version: 1.1
Name: endandicrypto
Version: 1.0.0
Summary: Send and receive cryptocurrency in a simple and intuitive way
Home-page: UNKNOWN
Author: Riccardo Verardi
Author-email: endandito@gmail.com
License: MIT
Keywords: endandicrypto
Platform: UNKNOWN
Classifier: Development Status :: 5 - Production/Stable
Classifier: Intended Audience :: Education
Classifier: Operating System :: Microsoft :: Windows :: Windows 10
Classifier: License :: OSI Approved :: MIT License
Classifier: Programming Language :: Python :: 3
